gpt_2_finetuning/__init__.py
gpt_2_finetuning/accumulate.py
gpt_2_finetuning/conditional_sample_model.py
gpt_2_finetuning/encoder.py
gpt_2_finetuning/generate_unconditional_samples.py
gpt_2_finetuning/interactive_conditional_samples.py
gpt_2_finetuning/load_dataset.py
gpt_2_finetuning/memory_saving_gradients.py
gpt_2_finetuning/model.py
gpt_2_finetuning/sample.py
gpt_2_finetuning/train.py
gpt_2_finetuning-1.0.14.data/scripts/download_gpt2_model
gpt_2_finetuning-1.0.14.dist-info/LICENSE
gpt_2_finetuning-1.0.14.dist-info/METADATA
gpt_2_finetuning-1.0.14.dist-info/WHEEL
gpt_2_finetuning-1.0.14.dist-info/top_level.txt
gpt_2_finetuning-1.0.14.dist-info/RECORD
