Metadata-Version: 2.1
Name: gpt-2-finetuning
Version: 1.0.14
Summary: Package for finetuning GPT-2 models
Home-page: https://github.com/jonheng/gpt-2-finetuning
Author: Jonathan Heng
Author-email: jonheng@users.noreply.github.com
License: MIT
Keywords: language model,machine learning,gpt2
Platform: UNKNOWN
Classifier: Programming Language :: Python :: 3
Classifier: License :: OSI Approved :: MIT License
Requires-Dist: numpy
Requires-Dist: regex
Requires-Dist: requests
Requires-Dist: tqdm
Requires-Dist: toposort
